Workbook

Sheet 使い方
A1: 業務改革 工程別タスクと成果物一覧
A2: 小説『平熱』第6.1話・第6.2話（切り替えの夜 上・下）に出てくる型・手法を、業務改革プロジェクトの工程ごとのタスクと成果物に紐づけた一覧。
A4: シート
A5: タスク一覧：工程×タスク。各タスクに狙い、使う型（物語での呼び方と正式名称）、主な成果物とその中身、実行する人、決める人、完了の条件、落とし穴、出典（話・章）。
A6: 成果物一覧：成果物ごとの目的、主な項目、作る人、承認する人、更新のタイミング、関連する型。関連タスク数は「タスク一覧」から数式で数える。
A7: 型の索引：上下巻の付録に載った型と用語の一覧（物語での呼び方、正式名称、型の中身・いつ使うか）。
A8: 工程サマリー：工程ごとのタスク数と成果物数（数式）、節目と判断者。
A10: 使い方
A11: 1. 自分の案件の工程に合わせて「タスク一覧」を上から読み、該当タスクの「完了の条件」を満たしているかを確かめる。
A12: 2. 満たしていないタスクの「成果物」を、「成果物一覧」の主な項目に沿って作る。
A13: 3. 議論に詰まったら「型の索引」で軸を探し、枠に入れて話す。枠に入らなければ壊す。
A15: 編集してよい列
... A21: scioltoharumi/dx-novels content/ch06.1_…（上）、ch06.2_…（下）、docs/ch06_業務改革の考え方一覧.md（2026-09-22）

Sheet 工程サマリー
A1: 工程 | B1: タスク数 | C1: 成果物数 | D1: 節目・判断（誰が）
A2: 1. 現状分析（As-Is） | B2: =COUNTIF(タスク一覧!$B:$B,A2) -> 12 | C2: =COUNTIF(成果物一覧!$B:$B,A2) -> 12 | D2: As-Is 報告を経営者が読み、痛みを数字で言い直せる（PM→社長）
A3: 2. 構想（To-Be・構想書） | B3: =COUNTIF(タスク一覧!$B:$B,A3) -> 21 | C3: =COUNTIF(成果物一覧!$B:$B,A3) -> 17 | D3: 構想書に社長が印を押す。節目①（社長）
A4: 3. 要件定義 | B4: =COUNTIF(タスク一覧!$B:$B,A4) -> 12 | C4: =COUNTIF(成果物一覧!$B:$B,A4) -> 10 | D4: 要件定義書 v1.0 を凍結し四人が署名、ステコミ承認。節目②（社長）
A5: 4. 選定・契約 | B5: =COUNTIF(タスク一覧!$B:$B,A5) -> 12 | C5: =COUNTIF(成果物一覧!$B:$B,A5) -> 10 | D5: 選定と契約をステコミで承認。予算超過は理由付き（社長）
A6: 5. 設計 | B6: =COUNTIF(タスク一覧!$B:$B,A6) -> 6 | C6: =COUNTIF(成果物一覧!$B:$B,A6) -> 3 | D6: 基本設計書 v1.0 を業務オーナーが承認（業務オーナー）
A7: 6. 開発・プロジェクト管理 | B7: =COUNTIF(タスク一覧!$B:$B,A7) -> 8 | C7: =COUNTIF(成果物一覧!$B:$B,A7) -> 6 | D7: クリティカルパスの節目を通過条件で判定（PM）
A8: 7. テスト | B8: =COUNTIF(タスク一覧!$B:$B,A8) -> 6 | C8: =COUNTIF(成果物一覧!$B:$B,A8) -> 6 | D8: UAT 合格に四人が署名。節目③（業務オーナー）
A9: 8. 移行・切替 | B9: =COUNTIF(タスク一覧!$B:$B,A9) -> 8 | C9: =COUNTIF(成果物一覧!$B:$B,A9) -> 8 | D9: カットオーバー判定表に社長が印を押す（社長）
A10: 9. 定着・運用 | B10: =COUNTIF(タスク一覧!$B:$B,A10) -> 9 | C10: =COUNTIF(成果物一覧!$B:$B,A10) -> 8 | D10: 効果測定を経営会議で報告し「平熱」を確かめる（社長）
A11: 合計 | B11: =SUM(B2:B10) -> 94 | C11: =SUM(C2:C10) -> 80
A13: 注：タスク数・成果物数は各シートの「工程」列を COUNTIF で数えた数式。工程名を書き換えるときは三シートで揃えること。

Sheet タスク一覧
A1: ID | B1: 工程 | C1: 時期（例） | D1: タスク | E1: 狙い | F1: 型（物語での呼び方） | G1: 正式名称 | H1: 主な成果物 | I1: 成果物の中身 | J1: 実行する人 | K1: 決める人 | L1: 完了の条件 | M1: 落とし穴 | N1: 出典
A2: T01 | B2: 1. 現状分析（As-Is） | C2: 7月 | D2: 改善か改革かを経営者に確かめる | E2: 経営者の言葉（手段）を目的に翻訳し、速くするのか変えるのかを揃える | F2: 速くするか、変えるか | G2: 業務改善と業務改革 | H2: プロジェクト前提メモ | I2: 目的の翻訳（痛み）、改善／改革の別、予算、期限、範囲外 | J2: PM | K2: 社長 | L2: 経営者が「改革」と認めた記録があり、予算と期限が数字で書いてある | M2: 改善のつもりの経営者と改革を始めて三か月後にぶつかる | N2: 6.1 第一章
A3: T02 | B3: 1. 現状分析（As-Is） | C3: 7月 | D3: 当たり（仮説）を置いてから数えに行く | E3: 見るものを絞る。外れも記録する | F3: 当たり | G3: 仮説思考 | H3: 仮説メモ | I3: 当たり（例：転記が原因）、当たりに関係する数え方、外れたときの記録欄 | J3: PM | K3: PM | L3: 当たりが一文で書かれ、数える項目がそれに紐づいている | M3: 当たりが無く、見たもの全部をメモして溺れる | N3: 6.1 第一章
A4: T03 | B4: 1. 現状分析（As-Is） | C4: 7月 | D4: 現場観察（部署ごとに一日ずつ張り付く） | E4: 手順書でなく実態を、件数・時間・金額で掴む | F4: 現場に張り付いて数える／現場・現物・現実 | G4: 現状業務分析（As-Is）／3現主義 | H4: 観察記録 | I4: 部署、担当者、作業、件数／日、分／件、使っている道具（Excel・メール） | J4: PM、PMO | K4: ― | L4: 三経路×受注・引当・出荷・請求・入金の全工程を、誰かが目で見た記録がある | M4: 手順書を写す。手順書に無いことが現場で起きている | N4: 6.1 第一章
A5: T04 | B5: 1. 現状分析（As-Is） | C5: 7月 | D5: 転記マップを作る | E5: 同じ数字を人が何回写すかを数える。事故の発生源を特定する | F5: 転記マップ | G5: 転記分析（データフロー図） | H5: 転記マップ | I5: 一件の数字が通る場所、写す回数、確認者の有無 | J5: PMO | K5: ― | L5: 代表的な一件について写す場所が番号付きで並び、確認者の有無が書いてある | M5: 写す回数を数えず「入力を速くする」施策に飛ぶ | N5: 6.1 第一章
A6: T05 | B6: 1. 現状分析（As-Is） | C6: 7月 | D6: リードタイムを作業時間と待ち時間に分ける | E6: 速くすべきは待ち時間だと示す | F6: 二日半のうち二十五分 | G6: リードタイム分析（待ち時間の可視化） | H6: リードタイム表 | I6: 受付から出荷までの工程、各工程の待ち時間と作業時間、合計 | J6: PMO | K6: ― | L6: 合計と作業時間の差（待ち）が数字で出ている | M6: 手を動かす時間だけ速くして、待ちが残る | N6: 6.1 第一章
A7: T06 | B7: 1. 現状分析（As-Is） | C7: 7月 | D7: 業務を頻度つきで棚卸しする | E7: 一週間の観察で見えない毎月・毎年を拾う | F7: 頻度つきの一覧 | G7: 業務棚卸し | H7: 業務一覧（頻度つき） | I7: 業務、担当、毎日／毎週／毎月／毎年、所要時間、使う帳票 | J7: PMO | K7: 業務オーナー | L7: 毎月・毎年の業務が入っている。帳票から逆引きして抜けを確かめた | M7: 本人が「仕事」と思っていないこと（返品＝後始末）が書かれない | N7: 6.1 第一章・第三章
A8: T07 | B8: 1. 現状分析（As-Is） | C8: 7月 | D8: 帳票の棚卸しと影の仕事の発見 | E8: 野良 Excel・個人の確認表を見つける | F8: 影の仕事 | G8: シャドーワーク（隠れ業務）／帳票棚卸し | H8: 帳票一覧、影の仕事リスト | I8: 帳票名、置き場所、作る人、使う人、手順書にあるか、無いと何が起きるか | J8: PMO | K8: ― | L8: 手順書に無い帳票と作業が別の行で挙がっている | M8: 影の仕事を本体の時間に足して、影が影でなくなる（残ると二重管理） | N8: 6.1 第一章
A9: T08 | B9: 1. 現状分析（As-Is） | C9: 7月 | D9: 業務フロー図（スイムレーン）を描く | E9: 部署の帯を跨ぐ矢印＝転記と待ちの数を見せる | F9: 帯を跨ぐ矢印 | G9: 業務フロー図（スイムレーン） | H9: As-Is 業務フロー図 | I9: 経路×工程の表、部署ごとの帯、帯を跨ぐ矢印の本数 | J9: PMO | K9: ― | L9: 三経路が同じ記法で描かれ、跨ぐ矢印が数えてある | M9: 経路ごとに別の記法で描いて差分が数えられない | N9: 6.1 第一章
A10: T09 | B10: 1. 現状分析（As-Is） | C10: 7月 | D10: 手作業を件数×時間×単価で金額にする | E10: 経営会議で通る言葉（金額）に落とす | F10: 定量化の三点セット | G10: 業務量調査 | H10: 手作業時間表 | I10: 担当ごとの件数、分／件、時間／月、合計、影の仕事（別行） | J10: PMO | K10: ― | L10: 合計時間と年額換算が出ている。自己申告は三割少ないことを注記 | M10: 声の大きい人の困りごとが大きく見える。同じ物差しで並べる | N10: 6.1 第一章
A11: T10 | B11: 1. 現状分析（As-Is） | C11: 7月 | D11: 事故を種類で分けて多い順に並べる | E11: 対策を上から打つ | F11: 多い順に並べる | G11: パレート分析 | H11: 事故一覧 | I11: 種類、件数、金額、取引先への影響、多い順 | J11: PMO | K11: ― | L11: 上位一〜二種類で大半を占めることが確かめられている | M11: 全部の事故に同じ力で当たる | N11: 6.1 第一章
A12: T11 | B12: 1. 現状分析（As-Is） | C12: 7月 | D12: 定常と非定常（月末・年度末）を分けて把握する | E12: 第二週に見えるものが月の全部ではない | F12: 月末×3 | G12: 定常・非定常の分離 | H12: 非定常業務メモ | I12: 月末・年度末・キャンペーン時の件数倍率と担当の稼働 | J12: PMO | K12: 業務オーナー | L12: 月末ピークの倍率が数字で書かれ、非機能要件の入力になっている | M12: 平日で試して月末に落ちる | N12: 6.1 第一章・第三章
... A95: T94 | B95: 9. 定着・運用 | C95: 4〜6月 | D95: 次のプロジェクトへ軸の一覧を引き継ぐ | E95: 一から枠を作らない。軸を先に置いて枠に入れて話す | F95: 軸の一覧 | G95: 整理軸 | H95: 軸の一覧（一枚） | I95: 二十本の軸、使う場面 | J95: PM | K95: ― | L95: 次の PM が軸の一覧を持って構想を書き始めている | M95: 毎回一からフレームを作る | N95: 6.2 終章

Sheet 成果物一覧
A1: 成果物 | B1: 工程 | C1: 目的 | D1: 主な項目 | E1: 作る人 | F1: 承認する人 | G1: 更新のタイミング | H1: 関連する型 | I1: 関連タスク数
A2: プロジェクト前提メモ | B2: 1. 現状分析（As-Is） | C2: 経営者の意図（改善／改革）と予算・期限を固定する | D2: 目的の翻訳、改善／改革、予算、期限、範囲外 | E2: PM | F2: 社長 | G2: 着手時。前提が変わったとき | H2: 業務改善と業務改革 | I2: =COUNTIF(タスク一覧!$H:$H,A2) -> 1
A3: 仮説メモ | B3: 1. 現状分析（As-Is） | C3: 数える対象を絞る | D3: 当たり、数える項目、外れの記録 | E3: PM | F3: ― | G3: 観察前。外れたとき | H3: 仮説思考 | I3: =COUNTIF(タスク一覧!$H:$H,A3) -> 1
A4: 観察記録 | B4: 1. 現状分析（As-Is） | C4: 実態を件数・時間で残す | D4: 部署、作業、件数、分／件、道具 | E4: PMO | F4: ― | G4: 観察の各日 | H4: 3現主義 | I4: =COUNTIF(タスク一覧!$H:$H,A4) -> 1
A5: 転記マップ | B5: 1. 現状分析（As-Is） | C5: 事故の発生源を示す | D5: 写す場所、回数、確認者 | E5: PMO | F5: ― | G5: 観察週。To-Be 設計時に再利用 | H5: 転記分析 | I5: =COUNTIF(タスク一覧!$H:$H,A5) -> 1
A6: リードタイム表 | B6: 1. 現状分析（As-Is） | C6: 待ち時間を示す | D6: 工程、待ち、作業、合計 | E6: PMO | F6: ― | G6: 観察週 | H6: リードタイム分析 | I6: =COUNTIF(タスク一覧!$H:$H,A6) -> 1
A7: 業務一覧（頻度つき） | B7: 1. 現状分析（As-Is） | C7: 毎月・毎年の業務を拾う | D7: 業務、担当、頻度、時間、帳票 | E7: PMO | F7: 業務オーナー | G7: 観察週。年に一度更新 | H7: 業務棚卸し | I7: =COUNTIF(タスク一覧!$H:$H,A7) -> 1
A8: 帳票一覧、影の仕事リスト | B8: 1. 現状分析（As-Is） | C8: 野良 Excel と隠れ業務を残す | D8: 帳票、置き場所、作る人、無いと何が起きるか | E8: PMO | F8: ― | G8: 観察週 | H8: シャドーワーク | I8: =COUNTIF(タスク一覧!$H:$H,A8) -> 1
A9: As-Is 業務フロー図 | B9: 1. 現状分析（As-Is） | C9: 経路の差分を数えられる形にする | D9: 経路×工程、スイムレーン、跨ぐ矢印 | E9: PMO | F9: ― | G9: 観察週。To-Be と同じ記法 | H9: 業務フロー図（スイムレーン） | I9: =COUNTIF(タスク一覧!$H:$H,A9) -> 1
A10: 手作業時間表 | B10: 1. 現状分析（As-Is） | C10: 金額で語る | D10: 担当、件数、時間、年額、影（別行） | E10: PMO | F10: ― | G10: 観察週。効果測定で比較 | H10: 業務量調査 | I10: =COUNTIF(タスク一覧!$H:$H,A10) -> 1
A11: 事故一覧 | B11: 1. 現状分析（As-Is） | C11: 対策の優先順位 | D11: 種類、件数、金額、影響 | E11: PMO | F11: ― | G11: 観察週 | H11: パレート分析 | I11: =COUNTIF(タスク一覧!$H:$H,A11) -> 1
A12: 非定常業務メモ | B12: 1. 現状分析（As-Is） | C12: 月末・年度末を非機能へつなぐ | D12: 倍率、担当の稼働 | E12: PMO | F12: 業務オーナー | G12: 観察週 | H12: 定常・非定常の分離 | I12: =COUNTIF(タスク一覧!$H:$H,A12) -> 1
A13: As-Is 報告（二枚） | B13: 1. 現状分析（As-Is） | C13: 痛みを数字で経営者に渡す | D13: 時間表、事故一覧の要約 | E13: PM | F13: 社長 | G13: 観察週の末 | H13: 経営課題・業務課題 | I13: =COUNTIF(タスク一覧!$H:$H,A13) -> 1
... A81: 朝礼メモ | B81: 9. 定着・運用 | C81: 経営者が短期成果を口にした記録 | D81: 日付、言葉、指標 | E81: 社長 | F81: ― | G81: 切替後三週間以内 | H81: 短期成果の見える化 | I81: =COUNTIF(タスク一覧!$H:$H,A81) -> 1
A83: 注：関連タスク数は「タスク一覧」の「主な成果物」列と成果物名が完全一致した行を数える。複数成果物を一つの行にまとめた成果物は 0 になることがある（名称は主な成果物と一致させてある）。

Sheet 型の索引
A1: 巻 | B1: 物語での呼び方 | C1: 正式名称 | D1: 型の中身・いつ使うか
A2: 上 | B2: 現場に張り付いて数える | C2: 現状業務分析（As-Is） | D2: 手順書でなく実態。件数・時間・金額に落とす。To-Be との差を測るために描く
A3: 上 | B3: 痛み | C3: 経営課題・業務課題 | D3: 「システムを入れろ」の裏にある目的。手段の言葉を目的に翻訳する
A4: 上 | B4: 速くするか、変えるか | C4: 業務改善と業務改革（Kaizen と BPR） | D4: 今の流れを速くするのが改善、流れ自体を変えるのが改革。最初にどちらの話かを確かめる
A5: 上 | B5: 現場・現物・現実 | C5: 3現主義 | D5: 手順書を写さず、現場で現物を見る。名前は後でいい
A6: 上 | B6: 当たり | C6: 仮説思考 | D6: 数えに行く前に「たぶん転記が原因」と置く。外れも記録する
A7: 上 | B7: 転記マップ | C7: 転記分析（データフロー図） | D7: 同じ数字を人が何回写すかを数える。写す場所が、誤読と事故の発生源
A8: 上 | B8: 二日半のうち二十五分 | C8: リードタイム分析（待ち時間の可視化） | D8: 作業時間と待ち時間を分ける。速くするなら待ち時間のほう
A9: 上 | B9: 頻度つきの一覧 | C9: 業務棚卸し | D9: 毎日・毎週・毎月・毎年で書き出す。一週間の観察では毎月と毎年が見えない。帳票から逆に引いて検証する
A10: 上 | B10: 影の仕事 | C10: シャドーワーク（隠れ業務） | D10: 手順書に無く、誰にも言っていない仕事。残すと二重管理になる。別の行に書く
A11: 上 | B11: 多い順に並べる | C11: パレート分析 | D11: 事故を種類で分け、多い順に。上の一つ二つで大半。対策は上から打つ
A12: 上 | B12: 声の大きい人 | C12: ヒアリングの偏り | D12: 声の大きい人の困りごとは大きく見える。同じ物差しで並べる
... A138: 下 | B138: 名前だけ | C138: EVM・BPMN・DMAIC | D138: 出来高で進捗を測る／業務フロー記法の標準／測ってから直す五段階。この規模では名前だけ知っておく
