Workbook

Sheet 使い方
A1: 業務改革プロジェクト 工程別タスク・成果物一覧（汎用版）
A2: 業務改革（BPR・業務システム導入）プロジェクトで、工程ごとに発生するタスクと、その成果物、完了基準、使う手法を紐づけた一覧。特定の案件や事例に依存しない汎用の型として整理している。
A4: シート構成
A5: 工程サマリー：九つの工程それぞれの目的、主な問い、節目（ゲート）と判断者、所要期間の目安、タスク数・成果物数（数式）。
A6: タスク一覧：工程×タスク。目的、主な成果物とその項目、実施者、承認者、完了基準、よくある失敗、使う手法・フレームワーク。
A7: 成果物一覧：成果物ごとの目的、主な項目、作成者、承認者、更新タイミング、関連手法、関連タスク数（数式）。
A8: 手法・フレームワーク索引：手法ごとの分類、概要、使う場面、使うときの要点。
A9: 整理軸：議論を枠に入れるための軸の一覧。一からフレームを作らずに済ませるための道具。
A11: 使い方
A12: 1. 案件の現在の工程で「タスク一覧」を上から読み、各タスクの「完了基準」を満たしているかを確認する。
A13: 2. 満たしていないタスクの成果物を、「成果物一覧」の主な項目に沿って作る。
A14: 3. 議論が詰まったら「整理軸」で軸を選び、枠に入れて話す。枠に入らない論点が出たら枠を壊してよい。
... A23: 工程列の色は工程の区別のみを表す。数式セル（タスク数・成果物数・関連タスク数）は書き換えない。

Sheet 工程サマリー
A1: 工程 | B1: 目的 | C1: 主な問い | D1: 節目（ゲート）と判断者 | E1: 所要期間の目安 | F1: タスク数 | G1: 成果物数
A2: 1. 現状分析（As-Is） | B2: 現状を件数・時間・金額で把握し、経営課題を数字に翻訳する | C2: 何が、どこで、どれだけ起きているか。手段の要望の裏にある目的は何か | D2: As-Is 報告を経営層が承認し、課題を数字で言い直せる（判断者：スポンサー） | E2: 2〜4 週 | F2: =COUNTIF(タスク一覧!$B:$B,A2) -> 12 | G2: =COUNTIF(成果物一覧!$B:$B,A2) -> 12
A3: 2. 構想策定（To-Be・構想書） | B3: 業務の変え方を先に決め、目的・効果・体制・対象外を一枚に固める | C3: 業務をどこまで変えるか。何をやらないか。誰が決めるか | D3: 構想書に経営層が承認（ゲート①。判断者：スポンサー） | E3: 3〜5 週 | F3: =COUNTIF(タスク一覧!$B:$B,A3) -> 21 | G3: =COUNTIF(成果物一覧!$B:$B,A3) -> 21
A4: 3. 要件定義 | B4: 無いと目的が達成できない要件を三層で書き、優先度を付けて凍結する | C4: 要件と要望の境目はどこか。合格の条件は何か | D4: 要件定義書 v1.0 を凍結し、業務オーナー署名と経営承認（ゲート②。判断者：スポンサー） | E4: 4〜8 週 | F4: =COUNTIF(タスク一覧!$B:$B,A4) -> 12 | G4: =COUNTIF(成果物一覧!$B:$B,A4) -> 12
A5: 4. 方式選定・調達・契約 | B5: 作る・買う・借りるを決め、基準で選び、境目と出口を契約に書く | C5: 自社の業務は独特か。総額と手作業で比べたか。出口はあるか | D5: 選定と契約を承認（判断者：スポンサー／ステアリングコミッティ） | E5: 4〜8 週 | F5: =COUNTIF(タスク一覧!$B:$B,A5) -> 12 | G5: =COUNTIF(成果物一覧!$B:$B,A5) -> 12
A6: 5. 設計 | B6: 設定・開発の前に紙で合意し、未決事項を業務オーナーに決めさせる | C6: 異常時に何が起きるか。決めていないことは何か | D6: 基本設計書 v1.0 を業務オーナーが承認（判断者：業務オーナー） | E6: 3〜6 週 | F6: =COUNTIF(タスク一覧!$B:$B,A6) -> 6 | G6: =COUNTIF(成果物一覧!$B:$B,A6) -> 6
A7: 6. 開発・プロジェクト管理 | B7: クリティカルパスに予備を置き、作業名で進捗を追い、変更を手順に乗せる | C7: 一日遅れたら期限が遅れる作業はどれか。残作業は何か | D7: 各マイルストーンを通過条件で判定（判断者：PM） | E7: 6〜12 週 | F7: =COUNTIF(タスク一覧!$B:$B,A7) -> 8 | G7: =COUNTIF(成果物一覧!$B:$B,A7) -> 8
A8: 7. テスト | B8: 異常系・境界値まで試し、修正のたびに全て流し、事前基準で受入判定する | C8: 正常系以外を試したか。修正で隣が壊れていないか | D8: UAT 合格に業務オーナーが署名（ゲート③。判断者：業務オーナー） | E8: 3〜6 週 | F8: =COUNTIF(タスク一覧!$B:$B,A8) -> 6 | G8: =COUNTIF(成果物一覧!$B:$B,A8) -> 6
A9: 8. 移行・本番切替 | B9: 戻せる形で切り替え、二回リハーサルし、表で判定する | C9: 戻す基準は何か。凍結中の取引はどうするか。誰も気づかない切替になっているか | D9: カットオーバー判定表に経営層が承認（判断者：スポンサー） | E9: 2〜4 週 | F9: =COUNTIF(タスク一覧!$B:$B,A9) -> 8 | G9: =COUNTIF(成果物一覧!$B:$B,A9) -> 8
A10: 9. 定着・運用移行 | B10: 使われない理由を四つに分けて手を打ち、運用設計と効果測定を残す | C10: 旧手段は残っていないか。効果は誰が測るか。終了後に誰が触るか | D10: 効果測定を経営会議で報告し、運用設計書を業務オーナーが承認（判断者：スポンサー／業務オーナー） | E10: 4〜12 週（効果測定は半年） | F10: =COUNTIF(タスク一覧!$B:$B,A10) -> 9 | G10: =COUNTIF(成果物一覧!$B:$B,A10) -> 9
A11: 合計 | F11: =SUM(F2:F10) -> 94 | G11: =SUM(G2:G10) -> 94
A13: 注：タスク数・成果物数は各シートの「工程」列を COUNTIF で数えた数式。所要期間は中規模案件の目安で、案件により大きく変わる。

Sheet タスク一覧
A1: ID | B1: 工程 | C1: タスク | D1: 目的 | E1: 主な成果物 | F1: 成果物の主な項目 | G1: 実施者 | H1: 承認者 | I1: 完了基準 | J1: よくある失敗 | K1: 使う手法・フレームワーク
A2: T01 | B2: 1. 現状分析（As-Is） | C2: 経営者の意図を確認し、改善か改革かを揃える | D2: 「システムを入れろ」等の手段の言葉を、解決したい経営課題（目的）に翻訳し、現行の高速化（改善）か業務の作り直し（改革）かを確定する | E2: プロジェクト前提メモ | F2: 背景、経営課題（目的）、改善／改革の別、予算上限、期限、対象外、判断者 | G2: PM | H2: スポンサー（経営層） | I2: 経営者が改善／改革の別と目的を自分の言葉で承認した記録があり、予算と期限が数字で書かれている | J2: 経営者は改善のつもり、推進側は改革のつもりで進め、数か月後に衝突する | K2: 業務改善と業務改革（Kaizen／BPR）の区別
A3: T02 | B3: 1. 現状分析（As-Is） | C3: 仮説を立ててから調査に入る | D3: 調査対象を絞り、集めた事実を判断に使える形にする。外れた仮説も記録する | E3: 仮説メモ | F3: 初期仮説、根拠、確認方法、確認結果（当たり／外れ） | G3: PM | H3: ― | I3: 仮説が一文で書かれ、調査項目がそれに紐づき、確認結果が追記されている | J3: 仮説なしで観察し、メモが山になって結論が出ない | K3: 仮説思考
A4: T03 | B4: 1. 現状分析（As-Is） | C4: 現場観察を行う（部署ごとに一日以上） | D4: 手順書ではなく実態を、件数・時間・金額で把握する | E4: 現場観察記録 | F4: 部署、担当者、作業、件数／日、分／件、使用ツール、手順書との差 | G4: PMO | H4: ― | I4: 対象業務の全工程を、誰かが現場で目視した記録がある。手順書と実態の差が列挙されている | J4: 手順書や既存資料の転記を現状分析と呼ぶ | K4: 3現主義（現場・現物・現実）
A5: T04 | B5: 1. 現状分析（As-Is） | C5: 転記・再入力箇所を数える | D5: 同じ情報を人が何回転記しているかを数え、ミスの発生源を特定する | E5: 転記マップ | F5: 代表的な一件の情報が通る経路、転記回数、各転記の確認者の有無 | G5: PMO | H5: ― | I5: 代表ケースについて転記箇所が番号付きで列挙され、確認者の有無が明記されている | J5: 転記回数を数えず「入力を速くする」施策に飛ぶ | K5: データフロー分析
A6: T05 | B6: 1. 現状分析（As-Is） | C6: リードタイムを作業時間と待ち時間に分解する | D6: 短縮すべきは作業時間より待ち時間であることを数字で示す | E6: リードタイム分析表 | F6: 工程、各工程の作業時間、待ち時間、合計、作業時間比率 | G6: PMO | H6: ― | I6: 合計リードタイムに対する待ち時間の比率が算出されている | J6: 手を動かす時間だけを速くし、待ち時間が残る | K6: リードタイム分析／バリューストリームマッピング
A7: T06 | B7: 1. 現状分析（As-Is） | C7: 業務を頻度つきで棚卸しする | D7: 短期の観察では見えない月次・年次業務を拾う | E7: 業務一覧（頻度つき） | F7: 業務名、担当、頻度（日／週／月／年）、所要時間、使用帳票、システム | G7: PMO | H7: 業務オーナー | I7: 月次・年次の業務が含まれ、帳票一覧から逆引きして抜けを確認した記録がある | J7: 担当者が「仕事」と認識していない業務（返品対応、後始末）が抜ける | K7: 業務棚卸し
A8: T07 | B8: 1. 現状分析（As-Is） | C8: 帳票と隠れ業務（個人管理の Excel 等）を洗い出す | D8: 公式手順に無い個人作業や野良ファイルを見つけ、移行と二重管理の対象を把握する | E8: 帳票一覧、隠れ業務リスト | F8: 帳票名、保管場所、作成者、利用者、手順書記載の有無、無い場合の影響 | G8: PMO | H8: ― | I8: 手順書に無い帳票・作業が別行で列挙されている | J8: 隠れ業務を本体の工数に合算し、対策対象として見えなくなる | K8: シャドーワーク分析／帳票棚卸し
A9: T08 | B9: 1. 現状分析（As-Is） | C9: 業務フロー図（スイムレーン）を描く | D9: 部署間の受け渡し（レーンを跨ぐ矢印）の数として転記と待ちを可視化する | E9: As-Is 業務フロー図 | F9: 経路×工程の表、部署別レーン、レーンを跨ぐ矢印の本数 | G9: PMO | H9: ― | I9: 全対象経路が同じ記法で描かれ、跨ぐ矢印が数えられている | J9: 経路ごとに記法が違い、差分が比較できない | K9: 業務フロー図（スイムレーン／BPMN）
A10: T09 | B10: 1. 現状分析（As-Is） | C10: 手作業を件数×時間×単価で金額換算する | D10: 経営判断に使える単位（金額）に落とす | E10: 業務量調査表 | F10: 担当別の件数、分／件、時間／月、年額換算、隠れ業務（別行） | G10: PMO | H10: ― | I10: 合計時間と年額換算が出ており、自己申告値の補正方法が注記されている | J10: 発言力の大きい部門の負荷が過大に、静かな部門の負荷が過小に見積もられる | K10: 業務量調査（タイムスタディ／ワークサンプリング）
A11: T10 | B11: 1. 現状分析（As-Is） | C11: 事故・ミスを分類し多い順に並べる | D11: 対策の優先順位を決める | E11: 事故・ミス一覧 | F11: 種類、件数、金額影響、取引先影響、発生頻度順 | G11: PMO | H11: ― | I11: 上位一〜二種類で大半を占めることが数字で確認できる | J11: 全種類に均等に対策を打つ | K11: パレート分析
A12: T11 | B12: 1. 現状分析（As-Is） | C12: 定常業務と非定常業務（月末・期末・繁忙期）を分けて把握する | D12: 観察期間に見えないピークを要件に反映する | E12: 非定常業務メモ | F12: 非定常の種類、発生時期、件数倍率、担当の稼働 | G12: PMO | H12: 業務オーナー | I12: ピーク時の件数倍率が数字で記録され、非機能要件の入力になっている | J12: 平常時で試験して月末に性能が出ない | K12: 定常・非定常の分離
... A95: T94 | B95: 9. 定着・運用移行 | C95: 型と軸を次のプロジェクトへ引き継ぐ | D95: 一からフレームを作らず、軸を先に置いて議論する | E95: 整理軸一覧 | F95: 使う軸、使う場面、使い方の注意 | G95: PM | H95: ― | I95: 次の PM が軸の一覧を持って構想を書き始めている | J95: 毎回一からフレームを作る | K95: 整理軸（軸の一覧）

Sheet 成果物一覧
A1: 成果物 | B1: 工程 | C1: 目的 | D1: 主な項目 | E1: 作成者 | F1: 承認者 | G1: 更新タイミング | H1: 関連手法 | I1: 関連タスク数
A2: プロジェクト前提メモ | B2: 1. 現状分析（As-Is） | C2: 経営者の意図と制約を固定する | D2: 目的、改善／改革の別、予算、期限、対象外、判断者 | E2: PM | F2: スポンサー（経営層） | G2: 着手時。前提が変わったとき | H2: 業務改善と業務改革の区別 | I2: =COUNTIF(タスク一覧!$E:$E,A2) -> 1
A3: 仮説メモ | B3: 1. 現状分析（As-Is） | C3: 調査対象を絞る | D3: 仮説、根拠、確認方法、結果 | E3: PM | F3: ― | G3: 調査前。結果判明時 | H3: 仮説思考 | I3: =COUNTIF(タスク一覧!$E:$E,A3) -> 1
A4: 現場観察記録 | B4: 1. 現状分析（As-Is） | C4: 実態を数字で残す | D4: 部署、作業、件数、時間、手順書との差 | E4: PMO | F4: ― | G4: 観察の各日 | H4: 3現主義 | I4: =COUNTIF(タスク一覧!$E:$E,A4) -> 1
A5: 転記マップ | B5: 1. 現状分析（As-Is） | C5: ミスの発生源を示す | D5: 転記箇所、回数、確認者 | E5: PMO | F5: ― | G5: 現状分析。To-Be 設計で再利用 | H5: データフロー分析 | I5: =COUNTIF(タスク一覧!$E:$E,A5) -> 1
A6: リードタイム分析表 | B6: 1. 現状分析（As-Is） | C6: 待ち時間を示す | D6: 工程、作業時間、待ち時間、比率 | E6: PMO | F6: ― | G6: 現状分析 | H6: リードタイム分析 | I6: =COUNTIF(タスク一覧!$E:$E,A6) -> 1
A7: 業務一覧（頻度つき） | B7: 1. 現状分析（As-Is） | C7: 月次・年次業務を拾う | D7: 業務、担当、頻度、時間、帳票 | E7: PMO | F7: 業務オーナー | G7: 現状分析。年一回更新 | H7: 業務棚卸し | I7: =COUNTIF(タスク一覧!$E:$E,A7) -> 1
A8: 帳票一覧、隠れ業務リスト | B8: 1. 現状分析（As-Is） | C8: 野良ファイルと隠れ業務を残す | D8: 帳票、保管場所、作成者、影響 | E8: PMO | F8: ― | G8: 現状分析 | H8: シャドーワーク分析 | I8: =COUNTIF(タスク一覧!$E:$E,A8) -> 1
A9: As-Is 業務フロー図 | B9: 1. 現状分析（As-Is） | C9: 差分を数えられる形にする | D9: レーン、工程、跨ぐ矢印 | E9: PMO | F9: ― | G9: 現状分析。To-Be と同一記法 | H9: 業務フロー図（スイムレーン） | I9: =COUNTIF(タスク一覧!$E:$E,A9) -> 1
A10: 業務量調査表 | B10: 1. 現状分析（As-Is） | C10: 金額で語る | D10: 担当、件数、時間、年額 | E10: PMO | F10: ― | G10: 現状分析。効果測定で比較 | H10: 業務量調査 | I10: =COUNTIF(タスク一覧!$E:$E,A10) -> 1
A11: 事故・ミス一覧 | B11: 1. 現状分析（As-Is） | C11: 優先順位を決める | D11: 種類、件数、影響 | E11: PMO | F11: ― | G11: 現状分析 | H11: パレート分析 | I11: =COUNTIF(タスク一覧!$E:$E,A11) -> 1
A12: 非定常業務メモ | B12: 1. 現状分析（As-Is） | C12: ピークを要件へ渡す | D12: 種類、時期、倍率 | E12: PMO | F12: 業務オーナー | G12: 現状分析 | H12: 定常・非定常の分離 | I12: =COUNTIF(タスク一覧!$E:$E,A12) -> 1
A13: As-Is 報告書 | B13: 1. 現状分析（As-Is） | C13: 課題を数字で経営層へ | D13: 工数、事故、転記、リードタイム | E13: PM | F13: スポンサー（経営層） | G13: 現状分析の末 | H13: 経営課題の翻訳 | I13: =COUNTIF(タスク一覧!$E:$E,A13) -> 1
... A95: 整理軸一覧 | B95: 9. 定着・運用移行 | C95: 型を一から作らない | D95: 軸、使う場面、注意 | E95: PM | F95: ― | G95: プロジェクトの末 | H95: 整理軸 | I95: =COUNTIF(タスク一覧!$E:$E,A95) -> 1
A97: 注：関連タスク数は「タスク一覧」の「主な成果物」列と成果物名が完全一致した行を数える数式。

Sheet 手法・フレームワーク索引
A1: 手法・フレームワーク | B1: 分類 | C1: 概要 | D1: 使う場面 | E1: 使うときの要点
A2: 業務改善と業務改革（Kaizen／BPR） | B2: 考え方 | C2: 現行の流れを速くするのが改善、流れ自体を作り直すのが改革 | D2: 着手時 | E2: 経営者と推進側でどちらの話かを最初に揃える
A3: 3現主義 | B3: 現状分析 | C3: 現場・現物・現実を自分で見る | D3: 現状分析 | E3: 手順書を写さない。手順書に無い動きが本命
A4: 仮説思考 | B4: 考え方 | C4: 調べる前に答えの当たりを置く | D4: 現状分析 | E4: 外れた仮説も記録する
A5: データフロー分析（転記マップ） | B5: 現状分析 | C5: 情報が人の手で写される箇所と回数を数える | D5: 現状分析 | E5: 転記箇所がミスの発生源
A6: リードタイム分析／VSM | B6: 現状分析 | C6: 工程を作業時間と待ち時間に分解 | D6: 現状分析 | E6: 短縮対象は待ち時間
A7: 業務棚卸し | B7: 現状分析 | C7: 業務を頻度つきで一覧化 | D7: 現状分析 | E7: 帳票から逆引きして抜けを確かめる
A8: シャドーワーク分析 | B8: 現状分析 | C8: 手順書に無い個人作業・野良ファイルを見つける | D8: 現状分析 | E8: 本体工数と分けて記録し、移行と二重管理の対象にする
A9: 業務フロー図（スイムレーン／BPMN） | B9: 現状分析 | C9: 部署別レーンで流れを描く | D9: 現状分析／To-Be | E9: レーンを跨ぐ矢印の数が転記と待ちの数
A10: 業務量調査（タイムスタディ／ワークサンプリング） | B10: 現状分析 | C10: 作業時間を測定し金額換算 | D10: 現状分析 | E10: 自己申告は少なく出る。発言力による偏りを補正
A11: パレート分析 | B11: 現状分析 | C11: 多い順に並べ上位に集中 | D11: 現状分析 | E11: 対策は上から打つ
A12: 定常・非定常の分離 | B12: 現状分析 | C12: 月末・期末・繁忙期を別に把握 | D12: 現状分析／要件定義 | E12: ピーク倍率を非機能要件へ
... A127: 整理軸（軸の一覧） | B127: 考え方 | C127: 先に軸を置いて枠に入れて議論する | D127: 全工程 | E127: 一からフレームを作らない。入らなければ壊す

Sheet 整理軸
A1: 軸 | B1: 目盛り・意味 | C1: 使う場面
A2: 改善／改革 | B2: 速くするのか、変えるのか | C2: 着手時
A3: As-Is／To-Be／Gap | B3: 現状、あるべき姿、その差 | C3: 全工程
A4: 業務／システム | B4: どちらの話か | C4: 論点整理
A5: あるべき姿／問題／課題／原因／真因 | B5: 問題は差、課題はやること | C5: 構想
A6: 人／プロセス／ルール／システム | B6: 原因の在処。システムで直せるのは一つ | C6: 構想
A7: 事実／解釈／行動（空・雨・傘） | B7: 報告書・構想書の行の分け方 | C7: 構想／報告
A8: 判断／処理／例外 | B8: 消えるのは処理 | C8: 構想／要件定義
A9: 要望／要件 | B9: あると嬉しい、ないと困る | C9: 要件定義
A10: 業務要件／機能要件／非機能要件 | B10: 三層で書き紐づける | C10: 要件定義
A11: Must／Should／Could／Won't | B11: 落とす順番 | C11: 要件定義
A12: 作る／買う／借りる | B12: 調達方式 | C12: 選定
... A25: 実行／責任／相談／報告（RACI） | B25: 体制 | C25: 構想
